{
  "sections": {
    "main": {
      "type": "main-product",
      "blocks": {
        "title": {
          "type": "title",
          "settings": {
            "heading_size": "ts:!text-lg"
          }
        },
        "vendor": {
          "type": "text",
          "settings": {
            "text": "{{ product.metafields.custom.category.value }}",
            "text_style": "subtitle"
          }
        },
        "price": {
          "type": "price",
          "settings": {}
        },
        "variant_picker": {
          "type": "variant_picker",
          "settings": {
            "picker_type": "button",
            "swatch_shape": "circle"
          }
        },
        "quantity_selector": {
          "type": "quantity_selector",
          "settings": {}
        },
        "buy_buttons": {
          "type": "buy_buttons",
          "settings": {
            "show_dynamic_checkout": false,
            "show_gift_card_recipient": false
          }
        },
        "description": {
          "type": "description",
          "disabled": true,
          "settings": {}
        },
        "collapsible_tab_7Wqwxn": {
          "type": "collapsible_tab",
          "settings": {
            "heading": "PRODUCT DESCRIPTIONS",
            "icon": "none",
            "content": "{{ product.description }}",
            "page": ""
          }
        },
        "collapsible_tab_R3xiTw": {
          "type": "collapsible_tab",
          "settings": {
            "heading": "Fit Details",
            "icon": "none",
            "content": "",
            "page": ""
          }
        },
        "collapsible_tab_Ab9Jrd": {
          "type": "collapsible_tab",
          "settings": {
            "heading": "CARE NOTES",
            "icon": "none",
            "content": "",
            "page": ""
          }
        },
        "collapsible_tab_zdTN6A": {
          "type": "collapsible_tab",
          "settings": {
            "heading": "Model Reference",
            "icon": "none",
            "content": "",
            "page": ""
          }
        },
        "collapsible_tab_8dtUp4": {
          "type": "collapsible_tab",
          "settings": {
            "heading": "Try It In Motion",
            "icon": "none",
            "content": "",
            "page": ""
          }
        }
      },
      "block_order": [
        "title",
        "vendor",
        "price",
        "variant_picker",
        "quantity_selector",
        "buy_buttons",
        "description",
        "collapsible_tab_7Wqwxn",
        "collapsible_tab_R3xiTw",
        "collapsible_tab_Ab9Jrd",
        "collapsible_tab_zdTN6A",
        "collapsible_tab_8dtUp4"
      ],
      "custom_css": [
        ".rte,.price {color: var(--ts-color-gray);}"
      ],
      "settings": {
        "enable_sticky_info": true,
        "color_scheme": "scheme-1",
        "media_size": "large",
        "constrain_to_viewport": true,
        "media_fit": "cover",
        "gallery_layout": "thumbnail",
        "mobile_thumbnails": "hide",
        "media_position": "left",
        "image_zoom": "hover",
        "hide_variants": false,
        "enable_video_looping": false,
        "padding_top": 36,
        "padding_bottom": 12
      }
    },
    "related-products": {
      "type": "related-products",
      "settings": {
        "heading": "You may also like",
        "heading_size": "h2",
        "products_to_show": 4,
        "columns_desktop": 4,
        "columns_mobile": "2",
        "color_scheme": "scheme-1",
        "image_ratio": "square",
        "image_shape": "default",
        "show_secondary_image": true,
        "show_vendor": false,
        "show_rating": false,
        "padding_top": 36,
        "padding_bottom": 28
      }
    }
  },
  "order": [
    "main",
    "related-products"
  ]
}
